spreadsheet_serializer/__init__.py
spreadsheet_serializer/apps.py
spreadsheet_serializer/core.py
spreadsheet_serializer/utils.py
spreadsheet_serializer/serializers/__init__.py
spreadsheet_serializer/serializers/ods_serializer.py
spreadsheet_serializer/serializers/xlsx_serializer.py
django_spreadsheet_serializer-0.1.0rc1.dist-info/METADATA
django_spreadsheet_serializer-0.1.0rc1.dist-info/WHEEL
django_spreadsheet_serializer-0.1.0rc1.dist-info/licenses/LICENSE
django_spreadsheet_serializer-0.1.0rc1.dist-info/RECORD
