Metadata-Version: 2.1
Name: django-spreadsheet-serializer
Version: 0.1.0rc1
Summary: Manage Django models using spreadsheets!
Project-URL: Homepage, https://github.com/paduszyk/django-spreadsheet-serializer
Project-URL: Documentation, https://github.com/paduszyk/django-spreadsheet-serializer#readme
Project-URL: Repository, https://github.com/paduszyk/django-spreadsheet-serializer
Author-email: Kamil Paduszyński <paduszyk@gmail.com>
Maintainer-email: Kamil Paduszyński <paduszyk@gmail.com>
License: MIT License
License-File: LICENSE
Keywords: Excel,django,ods,python,spreadsheet,xlsx
Classifier: Development Status :: 2 - Pre-Alpha
Classifier: Environment :: Console
Classifier: Framework :: Django
Classifier: Framework :: Django :: 3.2
Classifier: Framework :: Django :: 4.0
Classifier: Framework :: Django :: 4.1
Classifier: Framework :: Django :: 4.2
Classifier: Intended Audience :: Developers
Classifier: License :: OSI Approved :: MIT License
Classifier: Natural Language :: English
Classifier: Operating System :: OS Independent
Classifier: Programming Language :: Python :: 3
Classifier: Programming Language :: Python :: 3.8
Classifier: Programming Language :: Python :: 3.9
Classifier: Programming Language :: Python :: 3.10
Classifier: Programming Language :: Python :: 3.11
Classifier: Topic :: Database
Classifier: Topic :: File Formats
Classifier: Topic :: Software Development :: Libraries :: Python Modules
Requires-Python: >=3.8
Requires-Dist: odfpy
Requires-Dist: openpyxl
Requires-Dist: pandas
